mltinu/__init__.py
mltinu/builder.py
mltinu/cli.py
mltinu-0.1.5.dist-info/licenses/LICENSE
mltinu-0.1.5.dist-info/METADATA
mltinu-0.1.5.dist-info/WHEEL
mltinu-0.1.5.dist-info/entry_points.txt
mltinu-0.1.5.dist-info/top_level.txt
mltinu-0.1.5.dist-info/RECORD
